{
    "name": "Dipesh Kumar",
    "bio": "",
    "about": "",
    "socials": [
        {
            "name": "github",
            "icon": "fa-brands fa-github",
            "url": ""
        },
        {
            "name": "linkedin",
            "icon": "fa-brands fa-linkedin",
            "url": "https://www.linkedin.com/in/dipesh-kumar-9b0a1a1a0/"
        },
        {
            "name": "instagram",
            "icon": "fa-brands fa-instagram",
            "url": "https://www.instagram.com/dipeshkumar_/"
        },
        {
            "name": "medium",
            "icon": "fa-brands fa-medium",
            "url": ""
        },
        {
            "name": "email",
            "icon": "fa-solid fa-envelope",
            "url": "mailto:dipeshkrj14@gmail.com"
        }
    ],
    "skills": [
        {
            "name": "C",
            "icon": "devicon-c-plain"
        },
        {
            "name": "C++",
            "icon": "devicon-cplusplus-plain"
        },
        {
            "name": "Python",
            "icon": "devicon-python-plain"
        },
        {
            "name": "Javascript",
            "icon": "devicon-javascript-plain"
        },
        {
            "name": "C#",
            "icon": "devicon-csharp-plain"
        },
        {
            "name": "MySQL",
            "icon": "devicon-mysql-plain"
        },
        {
            "name": "Git",
            "icon": "devicon-git-plain"
        },
        {
            "name": "Fast API",
            "icon": "devicon-fastapi-plain"
        },
        {
            "name": "OpenGL",
            "icon": "devicon-opengl-plain"
        },
        {
            "name": "HTML",
            "icon": "devicon-html5-plain"
        },
        {
            "name": "CSS",
            "icon": "devicon-css3-plain"
        },
        {
            "name": "Bootstrap",
            "icon": "devicon-bootstrap-plain"
        },
        {
            "name": "Angular JS",
            "icon": "devicon-angularjs-plain"
        },
        {
            "name": "NodeJS",
            "icon": "devicon-nodejs-plain"
        },
        {
            "name": ".NET",
            "icon": "devicon-dotnetcore-plain"
        },
        {
            "name": "Django",
            "icon": "devicon-django-plain"
        },
        {
            "name": "11ty",
            "icon": "devicon-eleventy-plain"
        },
        {
            "name": "PyTorch",
            "icon": "devicon-pytorch-plain"
        }
    ]
}